{
  "name":"深圳实验学校（高中部）"
  "name":"深圳中学"
  "name":"深圳外国语学校"
  "name":"深圳市高级中学"
  "name":"福田区红岭中学"
  "name":"宝安区宝安中学"
  "name":"深大附中"
  "name":"南山区育才中学"
  "name":"罗湖区翠园中学"
  "name":"南山区南山外国语学校（集团）滨海中学"
  "name":"宝安区新安中学"
  "name":"深圳市第二高级中学"
  "name":"深圳实验学校（中学部）"
  "name":"深圳市第二实验学校"
  "name":"龙岗区龙城高级中学"
  "name":"深圳科学高中"
  "name":"南山区南头中学"
  "name":"罗湖外语学校"
  "name":"南山区北师大南山附属学校中学部"
  "name":"深圳市石岩公学（公办班）"
  "name":"南山区华侨城中学"
  "name":"宝安区第一外国语学校"
  "name":"深圳市第三高级中学"
  "name":"深圳市耀华实验学校（普高班）"
  "name":"深圳市第二外国语学校"
  "name":"福田区福田中学"
  "name":"宝安区松岗中学"
  "name":"深圳市盐田高级中学"
  "name":"北大附中深圳南山分校（普高班）"
  "name":"深圳市第一职业技术学校（校本部普通班）"
  "name":"宝安区西乡中学"
  "name":"华中师范大学龙岗附属中学"
  "name":"福田外国语高级中学"
  "name":"深圳市第七高级中学"
  "name":"深圳市美术学校（普高）"
  "name":"福田区梅林中学"
  "name":"龙岗区平冈中学"
  "name":"罗湖区滨河中学"
  "name":"深圳市明珠学校"
  "name":"光明新区高级中学"
  "name":"龙华新区观澜中学"
  "name":"龙岗区布吉高级中学"
  "name":"深圳市福景外国语学校（普高班）"
  "name":"坪山高级中学"
  "name":"龙华新区龙华中学"
  "name":"宝安区沙井中学"
  "name":"光明新区光明中学"
  "name":"龙岗区横岗高级中学"
  "name":"深圳市平湖外国语学校"
  "name":"龙岗区布吉中学"
  "name":"深圳市石岩公学（民办班）"
  "name":"深圳（南山）中加学校"
  "name":"深圳市富源学校"
  "name":"深圳市沪教院福田实验学校(普高班）"
  "name":"深圳市菁华中英文实验中学"
  "name":"深圳东方英文书院"
  "name":"龙岗区东升学校"
  "name":"龙岗区建文中学"

}